ecs_engine/__init__.py
ecs_engine/component.py
ecs_engine/component_pool.py
ecs_engine/entity.py
ecs_engine/entity_admin.py
ecs_engine/entity_builder.py
ecs_engine/entity_manager.py
ecs_engine/events.py
ecs_engine/interfaces.py
ecs_engine/system.py
tests/__init__.py
tests/tests.py
ecs_engine-0.5.4.dist-info/METADATA
ecs_engine-0.5.4.dist-info/WHEEL
ecs_engine-0.5.4.dist-info/top_level.txt
ecs_engine-0.5.4.dist-info/RECORD
